heartbeat_sh/__init__.py
heartbeat_sh/heartbeat.py
heartbeat_sh-0.3.0.dist-info/LICENCE
heartbeat_sh-0.3.0.dist-info/METADATA
heartbeat_sh-0.3.0.dist-info/WHEEL
heartbeat_sh-0.3.0.dist-info/top_level.txt
heartbeat_sh-0.3.0.dist-info/RECORD
