Metadata-Version: 2.1
Name: heartbeat-sh
Version: 0.3.0
Summary: A client library for heartbeat.sh
Home-page: https://heartbeat.sh
Author: heartbeat.sh
Author-email: admin@heartbeat.sh
License: UNKNOWN
Project-URL: Source Code, https://github.com/heartbeat-sh/heartbeat.py
Platform: UNKNOWN
Classifier: Programming Language :: Python :: 3
Classifier: License :: OSI Approved :: MIT License
Classifier: Operating System :: OS Independent
Requires-Python: >=3.6
License-File: LICENCE
